{
    "meta": {
        "code": 200
    },
    "pagination": {},
    "data": [{
        "comments": {
            "count": 1
        },
        "created_time": "1488687745",
        "location": null,
        "filter": "Lark",
        "type": "image",
        "attribution": null,
        "user_has_liked": false,
        "likes": {
            "count": 41
        },
        "id": "1463541341933628104_4056124835",
        "link": "https://www.instagram.com/p/BRPixioDWrI/",
        "caption": {
            "id": "17851534447147885",
            "from": {
                "id": "4056124835",
                "profile_picture": "https://scontent.cdninstagram.com/t51.2885-19/s150x150/14547614_194590957612183_7883005631030886400_a.jpg",
                "username": "jack.ofnotrade",
                "full_name": "Jack Ofnotrade"
            },
            "created_time": "1488687745",
            "text": "#chinchin at @simisrestaurant.  It's a #Nigerian desert.  The #moimoi was also good \n#foodies #foodie #foodporn #food #instafood #instafoodie #goodeats #chicago #chicagofoodie #chicagofoodies #chicagofoodporn #chicagofood"
        },
        "images": {
            "thumbnail": {
                "url": "https://scontent.cdninstagram.com/t51.2885-15/s150x150/e35/17077119_935520289884521_5592367037973266432_n.jpg",
                "width": 150,
                "height": 150
            },
            "low_resolution": {
                "url": "https://scontent.cdninstagram.com/t51.2885-15/s320x320/e35/17077119_935520289884521_5592367037973266432_n.jpg",
                "width": 320,
                "height": 320
            },
            "standard_resolution": {
                "url": "/img/puffPuff.jpg",
                "width": 640,
                "height": 640
            }
        },
        "users_in_photo": [],
        "user": {
            "id": "4056124835",
            "profile_picture": "https://scontent.cdninstagram.com/t51.2885-19/s150x150/14547614_194590957612183_7883005631030886400_a.jpg",
            "username": "jack.ofnotrade",
            "full_name": "Jack Ofnotrade"
        },
        "tags": ["goodeats", "chicagofood", "instafoodie", "instafood", "moimoi", "chicagofoodporn", "nigerian", "chicagofoodies", "chicagofoodie", "foodporn", "food", "chinchin", "chicago", "foodie", "foodies"]
    }, {
        "comments": {
            "count": 0
        },
        "created_time": "1488159753",
        "location": null,
        "filter": "Lark",
        "type": "image",
        "attribution": null,
        "user_has_liked": false,
        "likes": {
            "count": 34
        },
        "id": "1459112227214564129_4056124835",
        "link": "https://www.instagram.com/p/BQ_ztcGjZsh/",
        "caption": {
            "id": "17852579158130039",
            "from": {
                "id": "4056124835",
                "profile_picture": "https://scontent.cdninstagram.com/t51.2885-19/s150x150/14547614_194590957612183_7883005631030886400_a.jpg",
                "username": "jack.ofnotrade",
                "full_name": "Jack Ofnotrade"
            },
            "created_time": "1488159753",
            "text": "#oven #baked #tomatoes.  Add a little #salt and #roast for 4 hours at 250.  Finish with #oliveoil \n#tomato #sundriedtomatoes  #foodies #foodie #foodporn #food #instafood #instafoodie #goodeats #chicago #chicagofoodie #chicagofoodies #chicagofoodporn #chicagofood"
        },
        "images": {
            "thumbnail": {
                "url": "https://scontent.cdninstagram.com/t51.2885-15/s150x150/e35/16906661_417127301966281_6122594967006216192_n.jpg",
                "width": 150,
                "height": 150
            },
            "low_resolution": {
                "url": "https://scontent.cdninstagram.com/t51.2885-15/s320x320/e35/16906661_417127301966281_6122594967006216192_n.jpg",
                "width": 320,
                "height": 320
            },
            "standard_resolution": {
                "url": "/img/tea.jpg",
                "width": 640,
                "height": 640
            }
        },
        "users_in_photo": [],
        "user": {
            "id": "4056124835",
            "profile_picture": "https://scontent.cdninstagram.com/t51.2885-19/s150x150/14547614_194590957612183_7883005631030886400_a.jpg",
            "username": "jack.ofnotrade",
            "full_name": "Jack Ofnotrade"
        },
        "tags": ["chicagofood", "oliveoil", "instafoodie", "chicagofoodporn", "oven", "chicagofoodie", "food", "chicago", "tomato", "roast", "foodies", "goodeats", "instafood", "chicagofoodies", "salt", "baked", "sundriedtomatoes", "foodie", "foodporn", "tomatoes"]
    }, {
        "comments": {
            "count": 1
        },
        "created_time": "1487611219",
        "location": null,
        "filter": "Clarendon",
        "type": "image",
        "attribution": null,
        "user_has_liked": false,
        "likes": {
            "count": 28
        },
        "id": "1454510791654888495_4056124835",
        "link": "https://www.instagram.com/p/BQvddvSj9Qv/",
        "caption": {
            "id": "17861849818098611",
            "from": {
                "id": "4056124835",
                "profile_picture": "https://scontent.cdninstagram.com/t51.2885-19/s150x150/14547614_194590957612183_7883005631030886400_a.jpg",
                "username": "jack.ofnotrade",
                "full_name": "Jack Ofnotrade"
            },
            "created_time": "1487611219",
            "text": "#bacon #wrapped #shallots #sauteed in #shallots, #garlic, #oliveoil, and white #wine.  Bit of #dill and #greenonion.  Used that good #olive #oil from @theoliveoilboom\n\n#foodies #foodie #foodporn #food #instafood #instafoodie #goodeats #chicago #chicagofoodie #chicagofoodies #chicagofoodporn #chicagofood"
        },
        "images": {
            "thumbnail": {
                "url": "https://scontent.cdninstagram.com/t51.2885-15/s150x150/e35/16906639_313108942420823_2910283403276320768_n.jpg",
                "width": 150,
                "height": 150
            },
            "low_resolution": {
                "url": "https://scontent.cdninstagram.com/t51.2885-15/s320x320/e35/16906639_313108942420823_2910283403276320768_n.jpg",
                "width": 320,
                "height": 320
            },
            "standard_resolution": {
                "url": "https://scontent.cdninstagram.com/t51.2885-15/s640x640/sh0.08/e35/16906639_313108942420823_2910283403276320768_n.jpg",
                "width": 640,
                "height": 640
            }
        },
        "users_in_photo": [],
        "user": {
            "id": "4056124835",
            "profile_picture": "https://scontent.cdninstagram.com/t51.2885-19/s150x150/14547614_194590957612183_7883005631030886400_a.jpg",
            "username": "jack.ofnotrade",
            "full_name": "Jack Ofnotrade"
        },
        "tags": ["oil", "chicagofood", "oliveoil", "instafoodie", "chicagofoodporn", "chicagofoodie", "food", "shallots", "dill", "chicago", "bacon", "greenonion", "foodies", "goodeats", "wine", "instafood", "sauteed", "chicagofoodies", "garlic", "wrapped", "foodie", "foodporn", "olive"]
    }, {
        "comments": {
            "count": 2
        },
        "created_time": "1486917085",
        "location": null,
        "filter": "Juno",
        "type": "image",
        "attribution": null,
        "user_has_liked": false,
        "likes": {
            "count": 25
        },
        "id": "1448687971892139085_4056124835",
        "link": "https://www.instagram.com/p/BQaxgjzAxRN/",
        "caption": {
            "id": "17871277798002676",
            "from": {
                "id": "4056124835",
                "profile_picture": "https://scontent.cdninstagram.com/t51.2885-19/s150x150/14547614_194590957612183_7883005631030886400_a.jpg",
                "username": "jack.ofnotrade",
                "full_name": "Jack Ofnotrade"
            },
            "created_time": "1486917085",
            "text": "#bacon wrapped #dates stuffed with #bluecheese, and a #goatcheese\nand #kale #salad for #breakfast.  Because I can.\n\n#Brunch #breakfastofchampions #foodies #foodie #foodporn #food #instafood #instafoodie #goodeats #chicago #chicagofoodie #chicagofoodies #chicagofoodporn #chicagofood"
        },
        "images": {
            "thumbnail": {
                "url": "https://scontent.cdninstagram.com/t51.2885-15/s150x150/e35/16585669_747202435443913_7811900978566791168_n.jpg",
                "width": 150,
                "height": 150
            },
            "low_resolution": {
                "url": "https://scontent.cdninstagram.com/t51.2885-15/s320x320/e35/16585669_747202435443913_7811900978566791168_n.jpg",
                "width": 320,
                "height": 320
            },
            "standard_resolution": {
                "url": "/img/simpeTable.jpg",
                "width": 640,
                "height": 640
            }
        },
        "users_in_photo": [],
        "user": {
            "id": "4056124835",
            "profile_picture": "https://scontent.cdninstagram.com/t51.2885-19/s150x150/14547614_194590957612183_7883005631030886400_a.jpg",
            "username": "jack.ofnotrade",
            "full_name": "Jack Ofnotrade"
        },
        "tags": ["goatcheese", "chicagofood", "instafoodie", "chicagofoodporn", "chicagofoodie", "food", "kale", "bluecheese", "chicago", "bacon", "foodies", "goodeats", "breakfastofchampions", "instafood", "breakfast", "brunch", "chicagofoodies", "salad", "dates", "foodie", "foodporn"]
    }, {
        "comments": {
            "count": 0
        },
        "created_time": "1486833531",
        "location": null,
        "filter": "Lark",
        "type": "image",
        "attribution": null,
        "user_has_liked": false,
        "likes": {
            "count": 32
        },
        "id": "1447987070458120064_4056124835",
        "link": "https://www.instagram.com/p/BQYSJGeA8eA/",
        "caption": {
            "id": "17872541047051766",
            "from": {
                "id": "4056124835",
                "profile_picture": "https://scontent.cdninstagram.com/t51.2885-19/s150x150/14547614_194590957612183_7883005631030886400_a.jpg",
                "username": "jack.ofnotrade",
                "full_name": "Jack Ofnotrade"
            },
            "created_time": "1486833531",
            "text": "#eggs over #beef #hash and #peppers\n\n#foodies #foodie #foodporn #food #instafood #instafoodie #goodeats #chicago #chicagofoodie #chicagofoodies #chicagofoodporn #chicagofood"
        },
        "images": {
            "thumbnail": {
                "url": "https://scontent.cdninstagram.com/t51.2885-15/s150x150/e35/16583866_1329756490397088_6959079060953628672_n.jpg",
                "width": 150,
                "height": 150
            },
            "low_resolution": {
                "url": "https://scontent.cdninstagram.com/t51.2885-15/s320x320/e35/16583866_1329756490397088_6959079060953628672_n.jpg",
                "width": 320,
                "height": 320
            },
            "standard_resolution": {
                "url": "/img/toasts.jpg",
                "width": 640,
                "height": 640
            }
        },
        "users_in_photo": [],
        "user": {
            "id": "4056124835",
            "profile_picture": "https://scontent.cdninstagram.com/t51.2885-19/s150x150/14547614_194590957612183_7883005631030886400_a.jpg",
            "username": "jack.ofnotrade",
            "full_name": "Jack Ofnotrade"
        },
        "tags": ["chicagofood", "instafoodie", "chicagofoodporn", "chicagofoodie", "food", "beef", "chicago", "foodies", "goodeats", "instafood", "chicagofoodies", "eggs", "hash", "peppers", "foodie", "foodporn"]
    }, {
        "comments": {
            "count": 0
        },
        "created_time": "1486799529",
        "location": null,
        "filter": "Lark",
        "type": "image",
        "attribution": null,
        "user_has_liked": false,
        "likes": {
            "count": 84
        },
        "id": "1447701838316063660_4056124835",
        "link": "https://www.instagram.com/p/BQXRSbVgkus/",
        "caption": {
            "id": "17848969651153578",
            "from": {
                "id": "4056124835",
                "profile_picture": "https://scontent.cdninstagram.com/t51.2885-19/s150x150/14547614_194590957612183_7883005631030886400_a.jpg",
                "username": "jack.ofnotrade",
                "full_name": "Jack Ofnotrade"
            },
            "created_time": "1486799529",
            "text": "First #homemade #meal in #Chicago: #beef and #peppers with #portobello #mushrooms with #potatoes \n#foodies #foodie #foodporn #food #instafood #instafoodie #goodeats #chicago #chicagofoodie #chicagofoodies #chicagofoodporn #chicagofood"
        },
        "images": {
            "thumbnail": {
                "url": "https://scontent.cdninstagram.com/t51.2885-15/s150x150/e35/16465661_1562316923786427_6318527891831259136_n.jpg",
                "width": 150,
                "height": 150
            },
            "low_resolution": {
                "url": "https://scontent.cdninstagram.com/t51.2885-15/s320x320/e35/16465661_1562316923786427_6318527891831259136_n.jpg",
                "width": 320,
                "height": 320
            },
            "standard_resolution": {
                "url": "https://scontent.cdninstagram.com/t51.2885-15/s640x640/sh0.08/e35/16465661_1562316923786427_6318527891831259136_n.jpg",
                "width": 640,
                "height": 640
            }
        },
        "users_in_photo": [],
        "user": {
            "id": "4056124835",
            "profile_picture": "https://scontent.cdninstagram.com/t51.2885-19/s150x150/14547614_194590957612183_7883005631030886400_a.jpg",
            "username": "jack.ofnotrade",
            "full_name": "Jack Ofnotrade"
        },
        "tags": ["mushrooms", "chicagofood", "portobello", "instafoodie", "meal", "chicagofoodporn", "homemade", "chicagofoodie", "food", "beef", "chicago", "foodies", "goodeats", "instafood", "chicagofoodies", "potatoes", "peppers", "foodie", "foodporn"]
    }, {
        "comments": {
            "count": 0
        },
        "created_time": "1483925562",
        "location": null,
        "filter": "Clarendon",
        "type": "image",
        "attribution": null,
        "user_has_liked": false,
        "likes": {
            "count": 23
        },
        "id": "1423593254188700038_4056124835",
        "link": "https://www.instagram.com/p/BPBnoWsj1GG/",
        "caption": {
            "id": "17846896285147632",
            "from": {
                "id": "4056124835",
                "profile_picture": "https://scontent.cdninstagram.com/t51.2885-19/s150x150/14547614_194590957612183_7883005631030886400_a.jpg",
                "username": "jack.ofnotrade",
                "full_name": "Jack Ofnotrade"
            },
            "created_time": "1483925562",
            "text": "#blueberry #pancakes with #strawberries on top and a side of #toasted #pomegranate #seeds\n\nServed with #maplesyrup, and an #orange #syrup made by @abujachef\n\n#Brunch #dc #dcfoodie #dcfoodies #dcfoodporn #dcfood #foodies #foodie #foodporn #food #instafood #instafoodie"
        },
        "images": {
            "thumbnail": {
                "url": "https://scontent.cdninstagram.com/t51.2885-15/s150x150/e35/15803115_368299970211847_2209439921339367424_n.jpg",
                "width": 150,
                "height": 150
            },
            "low_resolution": {
                "url": "https://scontent.cdninstagram.com/t51.2885-15/s320x320/e35/15803115_368299970211847_2209439921339367424_n.jpg",
                "width": 320,
                "height": 320
            },
            "standard_resolution": {
                "url": "https://scontent.cdninstagram.com/t51.2885-15/s640x640/sh0.08/e35/15803115_368299970211847_2209439921339367424_n.jpg",
                "width": 640,
                "height": 640
            }
        },
        "users_in_photo": [],
        "user": {
            "id": "4056124835",
            "profile_picture": "https://scontent.cdninstagram.com/t51.2885-19/s150x150/14547614_194590957612183_7883005631030886400_a.jpg",
            "username": "jack.ofnotrade",
            "full_name": "Jack Ofnotrade"
        },
        "tags": ["dcfoodporn", "instafoodie", "dc", "dcfoodies", "strawberries", "maplesyrup", "food", "toasted", "syrup", "orange", "blueberry", "foodies", "pomegranate", "instafood", "seeds", "brunch", "dcfood", "foodie", "pancakes", "foodporn", "dcfoodie"]
    }, {
        "comments": {
            "count": 0
        },
        "created_time": "1483855123",
        "location": null,
        "filter": "Juno",
        "type": "image",
        "attribution": null,
        "user_has_liked": false,
        "likes": {
            "count": 12
        },
        "id": "1423002374104923715_4056124835",
        "link": "https://www.instagram.com/p/BO_hR6vD75D/",
        "caption": {
            "id": "17868369796015351",
            "from": {
                "id": "4056124835",
                "profile_picture": "https://scontent.cdninstagram.com/t51.2885-19/s150x150/14547614_194590957612183_7883005631030886400_a.jpg",
                "username": "jack.ofnotrade",
                "full_name": "Jack Ofnotrade"
            },
            "created_time": "1483855123",
            "text": "#strawberry and #goatcheese, toasted.  See them being made in the previous post\n\n#dc #dcfoodie #dcfoodies #dcfoodporn #dcfood  #foodies #foodie #foodporn #food #instafood #instafoodie #midnightsnack"
        },
        "images": {
            "thumbnail": {
                "url": "https://scontent.cdninstagram.com/t51.2885-15/s150x150/e35/15877406_146986399127864_4490097809265000448_n.jpg",
                "width": 150,
                "height": 150
            },
            "low_resolution": {
                "url": "https://scontent.cdninstagram.com/t51.2885-15/s320x320/e35/15877406_146986399127864_4490097809265000448_n.jpg",
                "width": 320,
                "height": 320
            },
            "standard_resolution": {
                "url": "https://scontent.cdninstagram.com/t51.2885-15/s640x640/sh0.08/e35/15877406_146986399127864_4490097809265000448_n.jpg",
                "width": 640,
                "height": 640
            }
        },
        "users_in_photo": [],
        "user": {
            "id": "4056124835",
            "profile_picture": "https://scontent.cdninstagram.com/t51.2885-19/s150x150/14547614_194590957612183_7883005631030886400_a.jpg",
            "username": "jack.ofnotrade",
            "full_name": "Jack Ofnotrade"
        },
        "tags": ["foodies", "goatcheese", "dcfoodporn", "instafoodie", "instafood", "dc", "dcfoodies", "strawberry", "midnightsnack", "food", "dcfood", "foodie", "foodporn", "dcfoodie"]
    }, {
        "comments": {
            "count": 0
        },
        "created_time": "1483854947",
        "location": null,
        "filter": "Juno",
        "type": "video",
        "attribution": null,
        "user_has_liked": false,
        "likes": {
            "count": 18
        },
        "id": "1423000898565496494_4056124835",
        "videos": {
            "low_bandwidth": {
                "url": "https://scontent.cdninstagram.com/t50.2886-16/15968601_1122923864473397_6673242519184080896_n.mp4",
                "width": 480,
                "height": 480
            },
            "low_resolution": {
                "url": "https://scontent.cdninstagram.com/t50.2886-16/15968601_1122923864473397_6673242519184080896_n.mp4",
                "width": 480,
                "height": 480
            },
            "standard_resolution": {
                "url": "https://scontent.cdninstagram.com/t50.2886-16/15945262_1881399458770390_8170149333212069888_n.mp4",
                "width": 640,
                "height": 640
            }
        },
        "link": "https://www.instagram.com/p/BO_g8ciDt6u/",
        "caption": {
            "id": "17858574268109407",
            "from": {
                "id": "4056124835",
                "profile_picture": "https://scontent.cdninstagram.com/t51.2885-19/s150x150/14547614_194590957612183_7883005631030886400_a.jpg",
                "username": "jack.ofnotrade",
                "full_name": "Jack Ofnotrade"
            },
            "created_time": "1483854947",
            "text": "Toasting #goatcheese and #strawberries.  #Delicious.\n\n#midnightsnack #plating #dc #dcfoodie #dcfoodies #dcfoodporn #dcfood  #foodies #foodie #foodporn #food #instafood #instafoodie"
        },
        "images": {
            "thumbnail": {
                "url": "https://scontent.cdninstagram.com/t51.2885-15/s150x150/e15/15876206_592916647562425_3362563873524678656_n.jpg",
                "width": 150,
                "height": 150
            },
            "low_resolution": {
                "url": "https://scontent.cdninstagram.com/t51.2885-15/s320x320/e15/15876206_592916647562425_3362563873524678656_n.jpg",
                "width": 320,
                "height": 320
            },
            "standard_resolution": {
                "url": "https://scontent.cdninstagram.com/t51.2885-15/s640x640/e15/15876206_592916647562425_3362563873524678656_n.jpg",
                "width": 640,
                "height": 640
            }
        },
        "users_in_photo": [],
        "user": {
            "id": "4056124835",
            "profile_picture": "https://scontent.cdninstagram.com/t51.2885-19/s150x150/14547614_194590957612183_7883005631030886400_a.jpg",
            "username": "jack.ofnotrade",
            "full_name": "Jack Ofnotrade"
        },
        "tags": ["goatcheese", "dcfoodporn", "instafoodie", "dc", "dcfoodies", "strawberries", "midnightsnack", "food", "delicious", "foodies", "instafood", "plating", "dcfood", "foodie", "foodporn", "dcfoodie"]
    }, {
        "comments": {
            "count": 0
        },
        "created_time": "1483817331",
        "location": null,
        "filter": "Clarendon",
        "type": "image",
        "attribution": null,
        "user_has_liked": false,
        "likes": {
            "count": 10
        },
        "id": "1422685345766351968_4056124835",
        "link": "https://www.instagram.com/p/BO-ZMjFjqRg/",
        "caption": {
            "id": "17858735887100539",
            "from": {
                "id": "4056124835",
                "profile_picture": "https://scontent.cdninstagram.com/t51.2885-19/s150x150/14547614_194590957612183_7883005631030886400_a.jpg",
                "username": "jack.ofnotrade",
                "full_name": "Jack Ofnotrade"
            },
            "created_time": "1483817331",
            "text": "#roasting #redpeppers and \"#sundrying\" #tomatoes in the #oven.  Increases the #savory aspects of each\n\n#peppers #sundriedtomatoes #roasted #dc #dcfoodie #dcfoodies #dcfoodporn #dcfood \n#foodies #foodie #foodporn #food #instafood #instafoodie"
        },
        "images": {
            "thumbnail": {
                "url": "https://scontent.cdninstagram.com/t51.2885-15/s150x150/e35/15803553_212242179236608_3908192773597036544_n.jpg",
                "width": 150,
                "height": 150
            },
            "low_resolution": {
                "url": "https://scontent.cdninstagram.com/t51.2885-15/s320x320/e35/15803553_212242179236608_3908192773597036544_n.jpg",
                "width": 320,
                "height": 320
            },
            "standard_resolution": {
                "url": "https://scontent.cdninstagram.com/t51.2885-15/s640x640/sh0.08/e35/15803553_212242179236608_3908192773597036544_n.jpg",
                "width": 640,
                "height": 640
            }
        },
        "users_in_photo": [],
        "user": {
            "id": "4056124835",
            "profile_picture": "https://scontent.cdninstagram.com/t51.2885-19/s150x150/14547614_194590957612183_7883005631030886400_a.jpg",
            "username": "jack.ofnotrade",
            "full_name": "Jack Ofnotrade"
        },
        "tags": ["dcfoodporn", "instafoodie", "dc", "dcfoodies", "oven", "roasting", "food", "savory", "sundrying", "foodies", "dcfoodie", "instafood", "redpeppers", "roasted", "peppers", "dcfood", "sundriedtomatoes", "foodie", "foodporn", "tomatoes"]
    }, {
        "comments": {
            "count": 1
        },
        "created_time": "1483400918",
        "location": null,
        "filter": "Juno",
        "type": "image",
        "attribution": null,
        "user_has_liked": false,
        "likes": {
            "count": 40
        },
        "id": "1419192220947116111_4056124835",
        "link": "https://www.instagram.com/p/BOx-85FjPBP/",
        "caption": {
            "id": "17846510650171490",
            "from": {
                "id": "4056124835",
                "profile_picture": "https://scontent.cdninstagram.com/t51.2885-19/s150x150/14547614_194590957612183_7883005631030886400_a.jpg",
                "username": "jack.ofnotrade",
                "full_name": "Jack Ofnotrade"
            },
            "created_time": "1483400918",
            "text": "#sushi for lunch at @chinachilcano\n\n#spanish #dc #dcfoodie #dcfoodies #dcfoodporn #dcfood #foodies #foodie #foodporn #food #instafood #instafoodie"
        },
        "images": {
            "thumbnail": {
                "url": "https://scontent.cdninstagram.com/t51.2885-15/s150x150/e35/15802222_1793227930944755_5790351114624827392_n.jpg",
                "width": 150,
                "height": 150
            },
            "low_resolution": {
                "url": "https://scontent.cdninstagram.com/t51.2885-15/s320x320/e35/15802222_1793227930944755_5790351114624827392_n.jpg",
                "width": 320,
                "height": 320
            },
            "standard_resolution": {
                "url": "https://scontent.cdninstagram.com/t51.2885-15/s640x640/sh0.08/e35/15802222_1793227930944755_5790351114624827392_n.jpg",
                "width": 640,
                "height": 640
            }
        },
        "users_in_photo": [],
        "user": {
            "id": "4056124835",
            "profile_picture": "https://scontent.cdninstagram.com/t51.2885-19/s150x150/14547614_194590957612183_7883005631030886400_a.jpg",
            "username": "jack.ofnotrade",
            "full_name": "Jack Ofnotrade"
        },
        "tags": ["foodies", "dcfoodporn", "instafoodie", "instafood", "dc", "spanish", "dcfoodie", "dcfoodies", "food", "dcfood", "foodie", "foodporn", "sushi"]
    }, {
        "comments": {
            "count": 0
        },
        "created_time": "1482611612",
        "location": null,
        "filter": "Clarendon",
        "type": "image",
        "attribution": null,
        "user_has_liked": false,
        "likes": {
            "count": 25
        },
        "id": "1412571046716870151_4056124835",
        "link": "https://www.instagram.com/p/BOadeIDj44H/",
        "caption": {
            "id": "17856128608092872",
            "from": {
                "id": "4056124835",
                "profile_picture": "https://scontent.cdninstagram.com/t51.2885-19/s150x150/14547614_194590957612183_7883005631030886400_a.jpg",
                "username": "jack.ofnotrade",
                "full_name": "Jack Ofnotrade"
            },
            "created_time": "1482611612",
            "text": "#miseenplace \n#foodies #foodie #foodporn #food #instafood #instafoodie"
        },
        "images": {
            "thumbnail": {
                "url": "https://scontent.cdninstagram.com/t51.2885-15/s150x150/e35/15625286_1115398558578714_5063043598988083200_n.jpg",
                "width": 150,
                "height": 150
            },
            "low_resolution": {
                "url": "https://scontent.cdninstagram.com/t51.2885-15/s320x320/e35/15625286_1115398558578714_5063043598988083200_n.jpg",
                "width": 320,
                "height": 320
            },
            "standard_resolution": {
                "url": "https://scontent.cdninstagram.com/t51.2885-15/s640x640/sh0.08/e35/15625286_1115398558578714_5063043598988083200_n.jpg",
                "width": 640,
                "height": 640
            }
        },
        "users_in_photo": [],
        "user": {
            "id": "4056124835",
            "profile_picture": "https://scontent.cdninstagram.com/t51.2885-19/s150x150/14547614_194590957612183_7883005631030886400_a.jpg",
            "username": "jack.ofnotrade",
            "full_name": "Jack Ofnotrade"
        },
        "tags": ["foodies", "food", "miseenplace", "instafoodie", "instafood", "foodie", "foodporn"]
    }, {
        "comments": {
            "count": 0
        },
        "created_time": "1482571277",
        "location": null,
        "filter": "Lark",
        "type": "image",
        "attribution": null,
        "user_has_liked": false,
        "likes": {
            "count": 10
        },
        "id": "1412232687498590824_4056124835",
        "link": "https://www.instagram.com/p/BOZQiWejHpo/",
        "caption": {
            "id": "17868686812020939",
            "from": {
                "id": "4056124835",
                "profile_picture": "https://scontent.cdninstagram.com/t51.2885-19/s150x150/14547614_194590957612183_7883005631030886400_a.jpg",
                "username": "jack.ofnotrade",
                "full_name": "Jack Ofnotrade"
            },
            "created_time": "1482571277",
            "text": "#gingerale with #crushed #cranberries and #rosemery. The #rumcake and #icecream is courtesy of the @abujachef\n\n#foodies #foodie #foodporn #food #instafood #instafoodie"
        },
        "images": {
            "thumbnail": {
                "url": "https://scontent.cdninstagram.com/t51.2885-15/s150x150/e35/15623614_118316258666237_7206278115583066112_n.jpg",
                "width": 150,
                "height": 150
            },
            "low_resolution": {
                "url": "https://scontent.cdninstagram.com/t51.2885-15/s320x320/e35/15623614_118316258666237_7206278115583066112_n.jpg",
                "width": 320,
                "height": 320
            },
            "standard_resolution": {
                "url": "https://scontent.cdninstagram.com/t51.2885-15/s640x640/sh0.08/e35/15623614_118316258666237_7206278115583066112_n.jpg",
                "width": 640,
                "height": 640
            }
        },
        "users_in_photo": [],
        "user": {
            "id": "4056124835",
            "profile_picture": "https://scontent.cdninstagram.com/t51.2885-19/s150x150/14547614_194590957612183_7883005631030886400_a.jpg",
            "username": "jack.ofnotrade",
            "full_name": "Jack Ofnotrade"
        },
        "tags": ["crushed", "icecream", "instafoodie", "instafood", "cranberries", "foodporn", "rumcake", "food", "gingerale", "foodie", "foodies", "rosemery"]
    }, {
        "comments": {
            "count": 0
        },
        "created_time": "1482564410",
        "location": null,
        "filter": "Juno",
        "type": "image",
        "attribution": null,
        "user_has_liked": false,
        "likes": {
            "count": 12
        },
        "id": "1412175085704201224_4056124835",
        "link": "https://www.instagram.com/p/BOZDcIoDkQI/",
        "caption": {
            "id": "17868665662018400",
            "from": {
                "id": "4056124835",
                "profile_picture": "https://scontent.cdninstagram.com/t51.2885-19/s150x150/14547614_194590957612183_7883005631030886400_a.jpg",
                "username": "jack.ofnotrade",
                "full_name": "Jack Ofnotrade"
            },
            "created_time": "1482564410",
            "text": "#duck #larb from Bida Manda in # Raleigh, NC.  Was crazy good. #Laotian food is the best\n\n#foodies #foodie #foodporn #food #instafood #instafoodie"
        },
        "images": {
            "thumbnail": {
                "url": "https://scontent.cdninstagram.com/t51.2885-15/s150x150/e35/15624359_956284981169899_4065699510788030464_n.jpg",
                "width": 150,
                "height": 150
            },
            "low_resolution": {
                "url": "https://scontent.cdninstagram.com/t51.2885-15/s320x320/e35/15624359_956284981169899_4065699510788030464_n.jpg",
                "width": 320,
                "height": 320
            },
            "standard_resolution": {
                "url": "https://scontent.cdninstagram.com/t51.2885-15/s640x640/sh0.08/e35/15624359_956284981169899_4065699510788030464_n.jpg",
                "width": 640,
                "height": 640
            }
        },
        "users_in_photo": [],
        "user": {
            "id": "4056124835",
            "profile_picture": "https://scontent.cdninstagram.com/t51.2885-19/s150x150/14547614_194590957612183_7883005631030886400_a.jpg",
            "username": "jack.ofnotrade",
            "full_name": "Jack Ofnotrade"
        },
        "tags": ["foodies", "instafoodie", "instafood", "larb", "duck", "food", "laotian", "foodie", "foodporn"]
    }, {
        "comments": {
            "count": 1
        },
        "created_time": "1482470536",
        "location": null,
        "filter": "Clarendon",
        "type": "image",
        "attribution": null,
        "user_has_liked": false,
        "likes": {
            "count": 20
        },
        "id": "1411387614724653858_4056124835",
        "link": "https://www.instagram.com/p/BOWQY7IDIMi/",
        "caption": {
            "id": "17867695402019365",
            "from": {
                "id": "4056124835",
                "profile_picture": "https://scontent.cdninstagram.com/t51.2885-19/s150x150/14547614_194590957612183_7883005631030886400_a.jpg",
                "username": "jack.ofnotrade",
                "full_name": "Jack Ofnotrade"
            },
            "created_time": "1482470536",
            "text": "#sphegetti and #sausage with a bit of #parmesan.  Real #comfortfood here, folks\n\n#dc #dcfoodie #dcfoodies #dcfoodporn #dcfood \n#foodies #foodie #foodporn #food #instafood #instafoodie"
        },
        "images": {
            "thumbnail": {
                "url": "https://scontent.cdninstagram.com/t51.2885-15/s150x150/e35/15534613_222042831576419_8636502650352828416_n.jpg",
                "width": 150,
                "height": 150
            },
            "low_resolution": {
                "url": "https://scontent.cdninstagram.com/t51.2885-15/s320x320/e35/15534613_222042831576419_8636502650352828416_n.jpg",
                "width": 320,
                "height": 320
            },
            "standard_resolution": {
                "url": "https://scontent.cdninstagram.com/t51.2885-15/s640x640/sh0.08/e35/15534613_222042831576419_8636502650352828416_n.jpg",
                "width": 640,
                "height": 640
            }
        },
        "users_in_photo": [],
        "user": {
            "id": "4056124835",
            "profile_picture": "https://scontent.cdninstagram.com/t51.2885-19/s150x150/14547614_194590957612183_7883005631030886400_a.jpg",
            "username": "jack.ofnotrade",
            "full_name": "Jack Ofnotrade"
        },
        "tags": ["foodies", "dcfoodporn", "sphegetti", "sausage", "instafoodie", "parmesan", "dc", "instafood", "dcfoodies", "comfortfood", "food", "dcfood", "foodie", "foodporn", "dcfoodie"]
    }, {
        "comments": {
            "count": 0
        },
        "created_time": "1482470317",
        "location": null,
        "filter": "Hudson",
        "type": "image",
        "attribution": null,
        "user_has_liked": false,
        "likes": {
            "count": 20
        },
        "id": "1411385779440014306_4056124835",
        "link": "https://www.instagram.com/p/BOWP-N4j1Pi/",
        "caption": {
            "id": "17845888687146149",
            "from": {
                "id": "4056124835",
                "profile_picture": "https://scontent.cdninstagram.com/t51.2885-19/s150x150/14547614_194590957612183_7883005631030886400_a.jpg",
                "username": "jack.ofnotrade",
                "full_name": "Jack Ofnotrade"
            },
            "created_time": "1482470317",
            "text": "#duck #confit #tacos from \"the #fancy #taco place\" in #SaltLakeCity, #Utah\n\n#foodies #foodie #foodporn #food #instafood #instafoodie"
        },
        "images": {
            "thumbnail": {
                "url": "https://scontent.cdninstagram.com/t51.2885-15/s150x150/e35/15538814_1704270739883506_5517726253035028480_n.jpg",
                "width": 150,
                "height": 150
            },
            "low_resolution": {
                "url": "https://scontent.cdninstagram.com/t51.2885-15/s320x320/e35/15538814_1704270739883506_5517726253035028480_n.jpg",
                "width": 320,
                "height": 320
            },
            "standard_resolution": {
                "url": "https://scontent.cdninstagram.com/t51.2885-15/s640x640/sh0.08/e35/15538814_1704270739883506_5517726253035028480_n.jpg",
                "width": 640,
                "height": 640
            }
        },
        "users_in_photo": [],
        "user": {
            "id": "4056124835",
            "profile_picture": "https://scontent.cdninstagram.com/t51.2885-19/s150x150/14547614_194590957612183_7883005631030886400_a.jpg",
            "username": "jack.ofnotrade",
            "full_name": "Jack Ofnotrade"
        },
        "tags": ["foodies", "saltlakecity", "instafoodie", "confit", "instafood", "duck", "food", "fancy", "taco", "foodie", "utah", "foodporn", "tacos"]
    }, {
        "comments": {
            "count": 0
        },
        "created_time": "1482470130",
        "location": null,
        "filter": "Clarendon",
        "type": "image",
        "attribution": null,
        "user_has_liked": false,
        "likes": {
            "count": 40
        },
        "id": "1411384205393072662_4056124835",
        "link": "https://www.instagram.com/p/BOWPnT8DRIW/",
        "caption": {
            "id": "17856040276089655",
            "from": {
                "id": "4056124835",
                "profile_picture": "https://scontent.cdninstagram.com/t51.2885-19/s150x150/14547614_194590957612183_7883005631030886400_a.jpg",
                "username": "jack.ofnotrade",
                "full_name": "Jack Ofnotrade"
            },
            "created_time": "1482470130",
            "text": "#stlouis style #beef #ribs from Bandit's Grill in #SaltLakeCity, #Utah.  Well done, guys.  The #hospitable #bartenders\n\n#foodies #foodie #foodporn #food #instafood #instafoodie"
        },
        "images": {
            "thumbnail": {
                "url": "https://scontent.cdninstagram.com/t51.2885-15/s150x150/e35/15624381_380377525631088_8752143326242668544_n.jpg",
                "width": 150,
                "height": 150
            },
            "low_resolution": {
                "url": "https://scontent.cdninstagram.com/t51.2885-15/s320x320/e35/15624381_380377525631088_8752143326242668544_n.jpg",
                "width": 320,
                "height": 320
            },
            "standard_resolution": {
                "url": "https://scontent.cdninstagram.com/t51.2885-15/s640x640/sh0.08/e35/15624381_380377525631088_8752143326242668544_n.jpg",
                "width": 640,
                "height": 640
            }
        },
        "users_in_photo": [],
        "user": {
            "id": "4056124835",
            "profile_picture": "https://scontent.cdninstagram.com/t51.2885-19/s150x150/14547614_194590957612183_7883005631030886400_a.jpg",
            "username": "jack.ofnotrade",
            "full_name": "Jack Ofnotrade"
        },
        "tags": ["stlouis", "foodies", "saltlakecity", "instafoodie", "hospitable", "instafood", "ribs", "bartenders", "food", "utah", "beef", "foodie", "foodporn"]
    }, {
        "comments": {
            "count": 0
        },
        "created_time": "1482469859",
        "location": null,
        "filter": "Normal",
        "type": "image",
        "attribution": null,
        "user_has_liked": false,
        "likes": {
            "count": 13
        },
        "id": "1411381937340074586_4056124835",
        "link": "https://www.instagram.com/p/BOWPGTpjspa/",
        "caption": {
            "id": "17868288379034053",
            "from": {
                "id": "4056124835",
                "profile_picture": "https://scontent.cdninstagram.com/t51.2885-19/s150x150/14547614_194590957612183_7883005631030886400_a.jpg",
                "username": "jack.ofnotrade",
                "full_name": "Jack Ofnotrade"
            },
            "created_time": "1482469859",
            "text": "Anonymous #breakfast from a #hotel in #Utah.  It was solid\n\n#castironskillet\n#foodies #foodie #foodporn #food #instafood #instafoodie"
        },
        "images": {
            "thumbnail": {
                "url": "https://scontent.cdninstagram.com/t51.2885-15/s150x150/e35/15624056_773469346125402_2365744170766696448_n.jpg",
                "width": 150,
                "height": 150
            },
            "low_resolution": {
                "url": "https://scontent.cdninstagram.com/t51.2885-15/s320x320/e35/15624056_773469346125402_2365744170766696448_n.jpg",
                "width": 320,
                "height": 320
            },
            "standard_resolution": {
                "url": "https://scontent.cdninstagram.com/t51.2885-15/s640x640/sh0.08/e35/15624056_773469346125402_2365744170766696448_n.jpg",
                "width": 640,
                "height": 640
            }
        },
        "users_in_photo": [],
        "user": {
            "id": "4056124835",
            "profile_picture": "https://scontent.cdninstagram.com/t51.2885-19/s150x150/14547614_194590957612183_7883005631030886400_a.jpg",
            "username": "jack.ofnotrade",
            "full_name": "Jack Ofnotrade"
        },
        "tags": ["hotel", "foodies", "instafoodie", "instafood", "breakfast", "castironskillet", "food", "utah", "foodie", "foodporn"]
    }, {
        "comments": {
            "count": 0
        },
        "created_time": "1482469617",
        "location": null,
        "filter": "Clarendon",
        "type": "image",
        "attribution": null,
        "user_has_liked": false,
        "likes": {
            "count": 41
        },
        "id": "1411379909050112592_4056124835",
        "link": "https://www.instagram.com/p/BOWOoyqDhpQ/",
        "caption": {
            "id": "17867564911025970",
            "from": {
                "id": "4056124835",
                "profile_picture": "https://scontent.cdninstagram.com/t51.2885-19/s150x150/14547614_194590957612183_7883005631030886400_a.jpg",
                "username": "jack.ofnotrade",
                "full_name": "Jack Ofnotrade"
            },
            "created_time": "1482469617",
            "text": "#friedchicken and #potatoes compliments of the @abujachef. #Delicious!\n\n#dc #dcfoodie #dcfoodies #dcfoodporn #dcfood \n#foodies #foodie #foodporn #food #instafood #instafoodie"
        },
        "images": {
            "thumbnail": {
                "url": "https://scontent.cdninstagram.com/t51.2885-15/s150x150/e35/15535173_224484491339660_1062692586839343104_n.jpg",
                "width": 150,
                "height": 150
            },
            "low_resolution": {
                "url": "https://scontent.cdninstagram.com/t51.2885-15/s320x320/e35/15535173_224484491339660_1062692586839343104_n.jpg",
                "width": 320,
                "height": 320
            },
            "standard_resolution": {
                "url": "https://scontent.cdninstagram.com/t51.2885-15/s640x640/sh0.08/e35/15535173_224484491339660_1062692586839343104_n.jpg",
                "width": 640,
                "height": 640
            }
        },
        "users_in_photo": [],
        "user": {
            "id": "4056124835",
            "profile_picture": "https://scontent.cdninstagram.com/t51.2885-19/s150x150/14547614_194590957612183_7883005631030886400_a.jpg",
            "username": "jack.ofnotrade",
            "full_name": "Jack Ofnotrade"
        },
        "tags": ["foodies", "dcfoodporn", "instafoodie", "instafood", "dc", "dcfoodies", "friedchicken", "potatoes", "food", "delicious", "dcfood", "foodie", "foodporn", "dcfoodie"]
    }, {
        "comments": {
            "count": 0
        },
        "created_time": "1482469216",
        "location": null,
        "filter": "Clarendon",
        "type": "image",
        "attribution": null,
        "user_has_liked": false,
        "likes": {
            "count": 21
        },
        "id": "1411376540570992545_4056124835",
        "link": "https://www.instagram.com/p/BOWN3xhDb-h/",
        "caption": {
            "id": "17867656792030681",
            "from": {
                "id": "4056124835",
                "profile_picture": "https://scontent.cdninstagram.com/t51.2885-19/s150x150/14547614_194590957612183_7883005631030886400_a.jpg",
                "username": "jack.ofnotrade",
                "full_name": "Jack Ofnotrade"
            },
            "created_time": "1482469216",
            "text": "#Salmon with #shallots and #meyer #lemon slices.  Side of #roasted #asparagus\n\n#dc #dcfoodie #dcfoodies #dcfoodporn #dcfood \n#foodies #foodie #foodporn #food #instafood #instafoodie"
        },
        "images": {
            "thumbnail": {
                "url": "https://scontent.cdninstagram.com/t51.2885-15/s150x150/e35/15535377_684141658431916_1141300555759484928_n.jpg",
                "width": 150,
                "height": 150
            },
            "low_resolution": {
                "url": "https://scontent.cdninstagram.com/t51.2885-15/s320x320/e35/15535377_684141658431916_1141300555759484928_n.jpg",
                "width": 320,
                "height": 320
            },
            "standard_resolution": {
                "url": "https://scontent.cdninstagram.com/t51.2885-15/s640x640/sh0.08/e35/15535377_684141658431916_1141300555759484928_n.jpg",
                "width": 640,
                "height": 640
            }
        },
        "users_in_photo": [],
        "user": {
            "id": "4056124835",
            "profile_picture": "https://scontent.cdninstagram.com/t51.2885-19/s150x150/14547614_194590957612183_7883005631030886400_a.jpg",
            "username": "jack.ofnotrade",
            "full_name": "Jack Ofnotrade"
        },
        "tags": ["meyer", "dcfoodporn", "salmon", "instafoodie", "dc", "dcfoodies", "shallots", "food", "lemon", "foodies", "instafood", "roasted", "asparagus", "dcfood", "foodie", "foodporn", "dcfoodie"]
    }]
}
